{
  "id": "4297709",
  "name": "EVmachineTest",
  "font_family": "iconfont",
  "css_prefix_text": "icon-",
  "description": "",
  "glyphs": [
    {
      "icon_id": "6072853",
      "name": "admin_Integration se",
      "font_class": "admin_Integrationse",
      "unicode": "e632",
      "unicode_decimal": 58930
    },
    {
      "icon_id": "15667077",
      "name": "生产量统计",
      "font_class": "shengchanliangtongji",
      "unicode": "e648",
      "unicode_decimal": 58952
    },
    {
      "icon_id": "28321131",
      "name": "效率",
      "font_class": "xiaoshuai",
      "unicode": "e640",
      "unicode_decimal": 58944
    },
    {
      "icon_id": "77110",
      "name": "时间",
      "font_class": "shijian",
      "unicode": "e600",
      "unicode_decimal": 58880
    },
    {
      "icon_id": "201648",
      "name": "3.1 时间",
      "font_class": "31shijian",
      "unicode": "e601",
      "unicode_decimal": 58881
    },
    {
      "icon_id": "335291",
      "name": "湿度",
      "font_class": "shidu",
      "unicode": "e60f",
      "unicode_decimal": 58895
    },
    {
      "icon_id": "398273",
      "name": "湿度",
      "font_class": "shidu1",
      "unicode": "e62f",
      "unicode_decimal": 58927
    },
    {
      "icon_id": "604480",
      "name": "报表",
      "font_class": "baobiao",
      "unicode": "e61b",
      "unicode_decimal": 58907
    },
    {
      "icon_id": "629339",
      "name": "时间",
      "font_class": "shijian1",
      "unicode": "e64d",
      "unicode_decimal": 58957
    },
    {
      "icon_id": "658039",
      "name": "时间",
      "font_class": "shijian2",
      "unicode": "e665",
      "unicode_decimal": 58981
    },
    {
      "icon_id": "761306",
      "name": "报表",
      "font_class": "icon",
      "unicode": "e654",
      "unicode_decimal": 58964
    },
    {
      "icon_id": "774445",
      "name": "报表",
      "font_class": "baobiao1",
      "unicode": "e65d",
      "unicode_decimal": 58973
    },
    {
      "icon_id": "1104404",
      "name": "报表2",
      "font_class": "baobiao2",
      "unicode": "e6d2",
      "unicode_decimal": 59090
    },
    {
      "icon_id": "1163700",
      "name": "报表",
      "font_class": "baobiao3",
      "unicode": "e655",
      "unicode_decimal": 58965
    },
    {
      "icon_id": "1305048",
      "name": "温度",
      "font_class": "wendu",
      "unicode": "e62e",
      "unicode_decimal": 58926
    },
    {
      "icon_id": "1305122",
      "name": "时间",
      "font_class": "shijian3",
      "unicode": "e638",
      "unicode_decimal": 58936
    },
    {
      "icon_id": "1314403",
      "name": "温度",
      "font_class": "wendu1",
      "unicode": "e66c",
      "unicode_decimal": 58988
    },
    {
      "icon_id": "1541994",
      "name": "温度",
      "font_class": "wendu2",
      "unicode": "e613",
      "unicode_decimal": 58899
    },
    {
      "icon_id": "1578768",
      "name": "报表",
      "font_class": "baobiao4",
      "unicode": "e652",
      "unicode_decimal": 58962
    },
    {
      "icon_id": "1638230",
      "name": "报表",
      "font_class": "baobiao5",
      "unicode": "e614",
      "unicode_decimal": 58900
    },
    {
      "icon_id": "1727448",
      "name": "217时间-线性",
      "font_class": "shijian-xianxing",
      "unicode": "e8c4",
      "unicode_decimal": 59588
    },
    {
      "icon_id": "1727450",
      "name": "217时间",
      "font_class": "shijian4",
      "unicode": "e8c5",
      "unicode_decimal": 59589
    },
    {
      "icon_id": "2076339",
      "name": "时间",
      "font_class": "shijian5",
      "unicode": "e8a9",
      "unicode_decimal": 59561
    },
    {
      "icon_id": "3145454",
      "name": "湿度",
      "font_class": "shidu2",
      "unicode": "e605",
      "unicode_decimal": 58885
    },
    {
      "icon_id": "3145460",
      "name": "温度",
      "font_class": "wendu3",
      "unicode": "e608",
      "unicode_decimal": 58888
    },
    {
      "icon_id": "4236632",
      "name": "湿度",
      "font_class": "shidu3",
      "unicode": "e60a",
      "unicode_decimal": 58890
    },
    {
      "icon_id": "4942660",
      "name": "时间",
      "font_class": "shijian6",
      "unicode": "e61d",
      "unicode_decimal": 58909
    },
    {
      "icon_id": "5040032",
      "name": "温度",
      "font_class": "jianzhuanquan",
      "unicode": "e60e",
      "unicode_decimal": 58894
    },
    {
      "icon_id": "5178942",
      "name": "温度",
      "font_class": "wendu4",
      "unicode": "e61e",
      "unicode_decimal": 58910
    },
    {
      "icon_id": "5387666",
      "name": "时间",
      "font_class": "shijian7",
      "unicode": "eb2a",
      "unicode_decimal": 60202
    },
    {
      "icon_id": "5653146",
      "name": "报表",
      "font_class": "baobiao6",
      "unicode": "e61c",
      "unicode_decimal": 58908
    },
    {
      "icon_id": "5831737",
      "name": "温度",
      "font_class": "wendu5",
      "unicode": "e694",
      "unicode_decimal": 59028
    },
    {
      "icon_id": "7335530",
      "name": "报表",
      "font_class": "baobiao7",
      "unicode": "eb2e",
      "unicode_decimal": 60206
    },
    {
      "icon_id": "7335567",
      "name": "温度",
      "font_class": "wendu6",
      "unicode": "eb37",
      "unicode_decimal": 60215
    },
    {
      "icon_id": "7335588",
      "name": "空气湿度",
      "font_class": "kongqishidu",
      "unicode": "eb3a",
      "unicode_decimal": 60218
    },
    {
      "icon_id": "7737999",
      "name": "报表 2",
      "font_class": "baobiao8",
      "unicode": "e602",
      "unicode_decimal": 58882
    },
    {
      "icon_id": "7991657",
      "name": "报表",
      "font_class": "baobiao9",
      "unicode": "e666",
      "unicode_decimal": 58982
    },
    {
      "icon_id": "10056242",
      "name": "报表",
      "font_class": "baobiao10",
      "unicode": "e707",
      "unicode_decimal": 59143
    },
    {
      "icon_id": "11110990",
      "name": "报表",
      "font_class": "baobiao11",
      "unicode": "e67c",
      "unicode_decimal": 59004
    },
    {
      "icon_id": "11372699",
      "name": "时间",
      "font_class": "shijian8",
      "unicode": "e8b8",
      "unicode_decimal": 59576
    },
    {
      "icon_id": "11372771",
      "name": "时间",
      "font_class": "shijian9",
      "unicode": "e8c6",
      "unicode_decimal": 59590
    },
    {
      "icon_id": "11536339",
      "name": "温度",
      "font_class": "wendu7",
      "unicode": "e797",
      "unicode_decimal": 59287
    },
    {
      "icon_id": "12331688",
      "name": "温度",
      "font_class": "wendu8",
      "unicode": "e66b",
      "unicode_decimal": 58987
    },
    {
      "icon_id": "12592400",
      "name": "报表",
      "font_class": "baobiao12",
      "unicode": "e74b",
      "unicode_decimal": 59211
    },
    {
      "icon_id": "12842736",
      "name": "w_湿度",
      "font_class": "w_shidu",
      "unicode": "e673",
      "unicode_decimal": 58995
    },
    {
      "icon_id": "12974860",
      "name": "报表",
      "font_class": "baobiao13",
      "unicode": "e62d",
      "unicode_decimal": 58925
    },
    {
      "icon_id": "13638743",
      "name": "温度",
      "font_class": "wendu9",
      "unicode": "e660",
      "unicode_decimal": 58976
    },
    {
      "icon_id": "15643715",
      "name": "报表",
      "font_class": "baobiao14",
      "unicode": "e6a9",
      "unicode_decimal": 59049
    },
    {
      "icon_id": "15726729",
      "name": "报表",
      "font_class": "baobiao15",
      "unicode": "e604",
      "unicode_decimal": 58884
    },
    {
      "icon_id": "17605421",
      "name": "温度",
      "font_class": "wendu10",
      "unicode": "e80f",
      "unicode_decimal": 59407
    },
    {
      "icon_id": "18267951",
      "name": "时间周期",
      "font_class": "shijianzhouqi",
      "unicode": "e996",
      "unicode_decimal": 59798
    },
    {
      "icon_id": "18610494",
      "name": "报表",
      "font_class": "baobiao16",
      "unicode": "e615",
      "unicode_decimal": 58901
    },
    {
      "icon_id": "23719352",
      "name": "湿度-1",
      "font_class": "shidu-1",
      "unicode": "e643",
      "unicode_decimal": 58947
    },
    {
      "icon_id": "25537593",
      "name": "温度",
      "font_class": "wendu11",
      "unicode": "e7d7",
      "unicode_decimal": 59351
    },
    {
      "icon_id": "25716508",
      "name": "空气湿度",
      "font_class": "kongqishidu1",
      "unicode": "ea33",
      "unicode_decimal": 59955
    },
    {
      "icon_id": "28606912",
      "name": "大气湿度",
      "font_class": "daqishidu",
      "unicode": "e6bd",
      "unicode_decimal": 59069
    },
    {
      "icon_id": "37288896",
      "name": "温度",
      "font_class": "wendu12",
      "unicode": "e656",
      "unicode_decimal": 58966
    },
    {
      "icon_id": "4354245",
      "name": "工业组件-仪表盘",
      "font_class": "gongyezujian-yibiaopan",
      "unicode": "eb94",
      "unicode_decimal": 60308
    },
    {
      "icon_id": "4354247",
      "name": "工业组件-指示灯",
      "font_class": "gongyezujian-zhishideng",
      "unicode": "eb96",
      "unicode_decimal": 60310
    },
    {
      "icon_id": "4354251",
      "name": "工业组件-开关",
      "font_class": "gongyezujian-kaiguan",
      "unicode": "eb98",
      "unicode_decimal": 60312
    },
    {
      "icon_id": "5735300",
      "name": "工业的-2",
      "font_class": "gongyede-",
      "unicode": "e758",
      "unicode_decimal": 59224
    },
    {
      "icon_id": "5735339",
      "name": "工业的-41",
      "font_class": "gongyede-1",
      "unicode": "e766",
      "unicode_decimal": 59238
    },
    {
      "icon_id": "14656265",
      "name": "工业设计",
      "font_class": "gongyesheji",
      "unicode": "e72f",
      "unicode_decimal": 59183
    },
    {
      "icon_id": "37506007",
      "name": "添加-L",
      "font_class": "tianjia-L",
      "unicode": "e610",
      "unicode_decimal": 58896
    },
    {
      "icon_id": "37506010",
      "name": "添加-圆-L",
      "font_class": "tianjia-yuan-L",
      "unicode": "e611",
      "unicode_decimal": 58897
    },
    {
      "icon_id": "37506012",
      "name": "禁用-L",
      "font_class": "jinyong-L",
      "unicode": "e612",
      "unicode_decimal": 58898
    },
    {
      "icon_id": "37507633",
      "name": "搜索-L",
      "font_class": "sousuo-L",
      "unicode": "e616",
      "unicode_decimal": 58902
    },
    {
      "icon_id": "37507646",
      "name": "菜单-L",
      "font_class": "caidan-L",
      "unicode": "e617",
      "unicode_decimal": 58903
    },
    {
      "icon_id": "37507649",
      "name": "刷新-L",
      "font_class": "shuaxin-L",
      "unicode": "e618",
      "unicode_decimal": 58904
    },
    {
      "icon_id": "37507654",
      "name": "保存-L",
      "font_class": "baocun-L",
      "unicode": "e619",
      "unicode_decimal": 58905
    },
    {
      "icon_id": "37507655",
      "name": "文本-L",
      "font_class": "wenben-L",
      "unicode": "e61a",
      "unicode_decimal": 58906
    },
    {
      "icon_id": "37538214",
      "name": "分析-L",
      "font_class": "fenxi-L",
      "unicode": "e62b",
      "unicode_decimal": 58923
    },
    {
      "icon_id": "37636066",
      "name": "主页03-L",
      "font_class": "zhuye03-L",
      "unicode": "e63b",
      "unicode_decimal": 58939
    },
    {
      "icon_id": "37639763",
      "name": "后退-L",
      "font_class": "houtui-L",
      "unicode": "e641",
      "unicode_decimal": 58945
    },
    {
      "icon_id": "37639765",
      "name": "前进-L",
      "font_class": "qianjin-L",
      "unicode": "e642",
      "unicode_decimal": 58946
    },
    {
      "icon_id": "37640485",
      "name": "用户-L",
      "font_class": "yonghu-L",
      "unicode": "e644",
      "unicode_decimal": 58948
    },
    {
      "icon_id": "37640496",
      "name": "登出-L",
      "font_class": "dengchu-L",
      "unicode": "e645",
      "unicode_decimal": 58949
    },
    {
      "icon_id": "37640503",
      "name": "退出-L",
      "font_class": "tuichu-L",
      "unicode": "e646",
      "unicode_decimal": 58950
    },
    {
      "icon_id": "37640506",
      "name": "登录-L",
      "font_class": "denglu-L",
      "unicode": "e647",
      "unicode_decimal": 58951
    },
    {
      "icon_id": "37649837",
      "name": "用户-删除-L",
      "font_class": "yonghu-shanchu-L",
      "unicode": "e649",
      "unicode_decimal": 58953
    },
    {
      "icon_id": "37649839",
      "name": "用户列表-L",
      "font_class": "yonghuliebiao-L",
      "unicode": "e64a",
      "unicode_decimal": 58954
    },
    {
      "icon_id": "37649840",
      "name": "用户-加-L",
      "font_class": "yonghu-jia-L",
      "unicode": "e64b",
      "unicode_decimal": 58955
    },
    {
      "icon_id": "37684055",
      "name": "更多",
      "font_class": "gengduo",
      "unicode": "1017a",
      "unicode_decimal": 65914
    },
    {
      "icon_id": "37684058",
      "name": "关闭",
      "font_class": "guanbi",
      "unicode": "1017b",
      "unicode_decimal": 65915
    },
    {
      "icon_id": "37684062",
      "name": "筛选",
      "font_class": "shaixuan",
      "unicode": "1017c",
      "unicode_decimal": 65916
    },
    {
      "icon_id": "37684063",
      "name": "设置",
      "font_class": "shezhi",
      "unicode": "1017d",
      "unicode_decimal": 65917
    },
    {
      "icon_id": "37684064",
      "name": "声明",
      "font_class": "shengming",
      "unicode": "1017e",
      "unicode_decimal": 65918
    },
    {
      "icon_id": "37684066",
      "name": "任务",
      "font_class": "renwu",
      "unicode": "1017f",
      "unicode_decimal": 65919
    },
    {
      "icon_id": "37684067",
      "name": "首页",
      "font_class": "shouye",
      "unicode": "10180",
      "unicode_decimal": 65920
    },
    {
      "icon_id": "37684078",
      "name": "我的",
      "font_class": "wode",
      "unicode": "10181",
      "unicode_decimal": 65921
    },
    {
      "icon_id": "37684089",
      "name": "帮助",
      "font_class": "bangzhu",
      "unicode": "10182",
      "unicode_decimal": 65922
    },
    {
      "icon_id": "37684090",
      "name": "提示",
      "font_class": "tishi",
      "unicode": "10183",
      "unicode_decimal": 65923
    }
  ]
}
